{"_type":"export","__export_format":4,"__export_date":"2020-09-29T23:39:52.205Z","__export_source":"insomnia.desktop.app:v2020.4.1","resources":[{"_id":"req_0077465c60284656b3e5c2f8a906868a","parentId":"fld_ffb6cd9610964ce69429029942b9bd54","modified":1601420115187,"created":1601417446231,"url":"{{ host }}/Pizzaria","name":"Store","description":"","method":"POST","body":{"mimeType":"application/json","text":"{\n\t\"nome\": \"Casa Blanca\",\n\t\"site\": \"www.casablanca.com\",\n\t\"telefone\": \"32355574\",\n\t\"cep\": \"38408510\",\n\t\"nmro_predio\": \"100\",\n\t\"abertura\": \"15:00:00\",\n\t\"fechamento\": \"23:00:00\",\n\t\"cpf_dono\": \"05651729133\"\n}"},"parameters":[],"headers":[{"name":"Content-Type","value":"application/json","id":"pair_972339b580744fb089a8ee31807a27b6"}],"authentication":{},"metaSortKey":-1601418619408,"isPrivate":false,"settingStoreCookies":true,"settingSendCookies":true,"settingDisableRenderRequestBody":false,"settingEncodeUrl":true,"settingRebuildPath":true,"settingFollowRedirects":"global","_type":"request"},{"_id":"fld_ffb6cd9610964ce69429029942b9bd54","parentId":"wrk_bb48b6339cf54b009fba3904155ad2f5","modified":1601417475695,"created":1601417436044,"name":"Pizzaria","description":"","environment":{},"environmentPropertyOrder":null,"metaSortKey":-1601347041640,"_type":"request_group"},{"_id":"wrk_bb48b6339cf54b009fba3904155ad2f5","parentId":null,"modified":1601347023100,"created":1601347023100,"name":"Trabalho - SBD","description":"","scope":null,"_type":"workspace"},{"_id":"req_ede8b6755f6c48f9baed8be66b8e656c","parentId":"fld_ffb6cd9610964ce69429029942b9bd54","modified":1601419072595,"created":1601418568307,"url":"{{ host }}/Pizzaria","name":"Index","description":"","method":"GET","body":{},"parameters":[],"headers":[],"authentication":{},"metaSortKey":-1601418619383,"isPrivate":false,"settingStoreCookies":true,"settingSendCookies":true,"settingDisableRenderRequestBody":false,"settingEncodeUrl":true,"settingRebuildPath":true,"settingFollowRedirects":"global","_type":"request"},{"_id":"req_dba60e77298c4eea800e9848837dad04","parentId":"fld_ffb6cd9610964ce69429029942b9bd54","modified":1601419291429,"created":1601418599331,"url":"{{ host }}/Pizzaria","name":"Update","description":"","method":"PUT","body":{"mimeType":"application/json","text":"{\n\t\"nome\": \"Minas Tche\",\n\t\"site\": \"www.minastche.com\",\n\t\"telefone\": \"32562587\",\n\t\"cep\": \"38408710\",\n\t\"nmro_predio\": \"80\",\n\t\"abertura\": \"17:00:00\",\n\t\"fechamento\": \"02:00:00\",\n\t\"cpf_dono\": \"05651729133\",\n\t\"id\": \"1\"\n}"},"parameters":[],"headers":[{"name":"Content-Type","value":"application/json","id":"pair_9a4a15b61e6741a0be1d13b7dd2eb829"}],"authentication":{},"metaSortKey":-1601418619370.5,"isPrivate":false,"settingStoreCookies":true,"settingSendCookies":true,"settingDisableRenderRequestBody":false,"settingEncodeUrl":true,"settingRebuildPath":true,"settingFollowRedirects":"global","_type":"request"},{"_id":"req_499f7a1386be47c796409cddaf5be1f3","parentId":"fld_ffb6cd9610964ce69429029942b9bd54","modified":1601420038114,"created":1601418619358,"url":"{{ host }}/Pizzaria","name":"Destroy","description":"","method":"DELETE","body":{"mimeType":"application/json","text":"{\n\t\"id\": \"2\" \n}"},"parameters":[],"headers":[{"name":"Content-Type","value":"application/json","id":"pair_1a107df0fa3c4e50b81e6d9d18f30dd6"}],"authentication":{},"metaSortKey":-1601418619358,"isPrivate":false,"settingStoreCookies":true,"settingSendCookies":true,"settingDisableRenderRequestBody":false,"settingEncodeUrl":true,"settingRebuildPath":true,"settingFollowRedirects":"global","_type":"request"},{"_id":"req_b0a94626bdc3414484ecdfd425e633ce","parentId":"fld_ab024cc14c964722b3ef5fc7b646fa1e","modified":1601420986751,"created":1601347053498,"url":"{{ host }}/dono","name":"Store","description":"","method":"POST","body":{"mimeType":"application/json","text":"{\n\t\"cpf\": \"11123527411\",\n\t\"nome\": \"Gabriel Domingues\",\n\t\"cep\": \"38408600\",\n\t\"linkedin\": \"gabrielhenriquedc@gmail.com\",\n\t\"data_nascimento\": \"11/03/1997\",\n\t\"nmro_residencia\": \"52\"\n}"},"parameters":[],"headers":[{"name":"Content-Type","value":"application/json","id":"pair_648f01fc48b944928838417f42acb64e"}],"authentication":{},"metaSortKey":-1601420135826,"isPrivate":false,"settingStoreCookies":true,"settingSendCookies":true,"settingDisableRenderRequestBody":false,"settingEncodeUrl":true,"settingRebuildPath":true,"settingFollowRedirects":"global","_type":"request"},{"_id":"fld_ab024cc14c964722b3ef5fc7b646fa1e","parentId":"wrk_bb48b6339cf54b009fba3904155ad2f5","modified":1601347041590,"created":1601347041590,"name":"Donos","description":"","environment":{},"environmentPropertyOrder":null,"metaSortKey":-1601347041590,"_type":"request_group"},{"_id":"req_0c3248b0fc1d430783dd132df26300c2","parentId":"fld_ab024cc14c964722b3ef5fc7b646fa1e","modified":1601421002254,"created":1601420135776,"url":"{{ host }}/dono","name":"Index","description":"","method":"GET","body":{},"parameters":[],"headers":[],"authentication":{},"metaSortKey":-1601420135776,"isPrivate":false,"settingStoreCookies":true,"settingSendCookies":true,"settingDisableRenderRequestBody":false,"settingEncodeUrl":true,"settingRebuildPath":true,"settingFollowRedirects":"global","_type":"request"},{"_id":"req_eb23f651c6cf4ec489d65eaa5b75924c","parentId":"fld_ab024cc14c964722b3ef5fc7b646fa1e","modified":1601421349159,"created":1601420156094,"url":"{{ host }}/dono","name":"Update","description":"","method":"PUT","body":{"mimeType":"application/json","text":"{\n\t\"cpf\": \"11123527411\",\n\t\"nome\": \"heitor henrique\",\n\t\"cep\": \"38402830\",\n\t\"linkedin\": \"heitor456@gmail.com\",\n\t\"data_nascimento\": \"20/07/2000\",\n\t\"nmro_residencia\": \"84\"\n}"},"parameters":[],"headers":[{"name":"Content-Type","value":"application/json","id":"pair_e92947951c974f11b4c3d6a62a7b42fa"}],"authentication":{},"metaSortKey":-1601420135726,"isPrivate":false,"settingStoreCookies":true,"settingSendCookies":true,"settingDisableRenderRequestBody":false,"settingEncodeUrl":true,"settingRebuildPath":true,"settingFollowRedirects":"global","_type":"request"},{"_id":"req_b18262f30fc94047ae2c2d8fecd60e2d","parentId":"fld_ab024cc14c964722b3ef5fc7b646fa1e","modified":1601421268891,"created":1601420172525,"url":"{{ host }}/dono","name":"Destroy","description":"","method":"DELETE","body":{"mimeType":"application/json","text":"{\n\t\"cpf\": \"11123527411\"\n}"},"parameters":[],"headers":[{"name":"Content-Type","value":"application/json","id":"pair_ca5d6ed0c99e4ddc96abb030721628e2"}],"authentication":{},"metaSortKey":-1601420135676,"isPrivate":false,"settingStoreCookies":true,"settingSendCookies":true,"settingDisableRenderRequestBody":false,"settingEncodeUrl":true,"settingRebuildPath":true,"settingFollowRedirects":"global","_type":"request"},{"_id":"env_6ed255e0db336d447c63402d02eb95b58432ffcb","parentId":"wrk_bb48b6339cf54b009fba3904155ad2f5","modified":1601347142632,"created":1601347023178,"name":"Base Environment","data":{"host":"http://localhost:3333"},"dataPropertyOrder":{"&":["host"]},"color":null,"isPrivate":false,"metaSortKey":1601347023178,"_type":"environment"},{"_id":"jar_6ed255e0db336d447c63402d02eb95b58432ffcb","parentId":"wrk_bb48b6339cf54b009fba3904155ad2f5","modified":1601347023183,"created":1601347023183,"name":"Default Jar","cookies":[],"_type":"cookie_jar"},{"_id":"spc_abd05edcd71c46fcbf8cfdd48d0b5f26","parentId":"wrk_bb48b6339cf54b009fba3904155ad2f5","modified":1601347023104,"created":1601347023104,"fileName":"Trabalho - SBD","contents":"","contentType":"yaml","_type":"api_spec"}]}